s3torchconnectorclient/__init__.py
s3torchconnectorclient/_logger_patch.py
s3torchconnectorclient/_mountpoint_s3_client.cpython-312-x86_64-linux-gnu.so
s3torchconnectorclient/_mountpoint_s3_client.pyi
s3torchconnectorclient/py.typed
s3torchconnectorclient-1.4.3.dist-info/METADATA
s3torchconnectorclient-1.4.3.dist-info/WHEEL
s3torchconnectorclient-1.4.3.dist-info/top_level.txt
s3torchconnectorclient-1.4.3.dist-info/RECORD
s3torchconnectorclient-1.4.3.dist-info/licenses/LICENSE
s3torchconnectorclient-1.4.3.dist-info/licenses/NOTICE
s3torchconnectorclient-1.4.3.dist-info/licenses/THIRD-PARTY-LICENSES
