Metadata-Version: 2.4
Name: s3torchconnectorclient
Version: 1.4.3
Summary: Internal S3 client implementation for s3torchconnector
Classifier: Development Status :: 5 - Production/Stable
Classifier: Programming Language :: Python :: 3
Classifier: Programming Language :: Python :: 3.8
Classifier: Programming Language :: Python :: 3.9
Classifier: Programming Language :: Python :: 3.10
Classifier: Programming Language :: Python :: 3.11
Classifier: Programming Language :: Python :: 3.12
Classifier: Programming Language :: Python :: 3.13
Classifier: License :: OSI Approved :: BSD License
Classifier: Operating System :: OS Independent
Classifier: Topic :: Utilities
Requires-Python: <3.14,>=3.8
License-File: LICENSE
License-File: THIRD-PARTY-LICENSES
License-File: NOTICE
Provides-Extra: test
Requires-Dist: boto3; extra == "test"
Requires-Dist: pytest; extra == "test"
Requires-Dist: pytest-timeout; extra == "test"
Requires-Dist: hypothesis; extra == "test"
Requires-Dist: flake8; extra == "test"
Requires-Dist: black; extra == "test"
Requires-Dist: mypy; extra == "test"
Requires-Dist: Pillow<=11.2.1; extra == "test"
Dynamic: license-file
